friendly_name_mixin.py
friendly_name_mixin-2.0.0.dist-info/AUTHORS
friendly_name_mixin-2.0.0.dist-info/LICENSE
friendly_name_mixin-2.0.0.dist-info/METADATA
friendly_name_mixin-2.0.0.dist-info/WHEEL
friendly_name_mixin-2.0.0.dist-info/top_level.txt
friendly_name_mixin-2.0.0.dist-info/RECORD
