Metadata-Version: 2.1
Name: friendly-name-mixin
Version: 2.0.0
Summary: Mixin class for extracting friendly names from classes
Home-page: https://github.com/petarmaric/friendly_name_mixin
Author: Petar Maric
Author-email: petarmaric@uns.ac.rs
License: BSD
Platform: any
Classifier: Development Status :: 5 - Production/Stable
Classifier: Intended Audience :: Developers
Classifier: License :: OSI Approved :: BSD License
Classifier: Operating System :: OS Independent
Classifier: Programming Language :: Python :: 3
Classifier: Topic :: Software Development
Classifier: Topic :: Utilities
License-File: LICENSE
License-File: AUTHORS
